railwaymap/__init__.py
railwaymap/example.py
railwaymap/json_data.py
railwaymap/railway_map.py
railwaymap_read_file/__init__.py
railwaymap_read_file/example.py
railwaymap_read_file/railway_map.py
railwaymap-0.0.3.dist-info/METADATA
railwaymap-0.0.3.dist-info/WHEEL
railwaymap-0.0.3.dist-info/top_level.txt
railwaymap-0.0.3.dist-info/RECORD
